ipicat/__init__.py
ipicat/pi.py
ipicat/static/picat.js
ipicat-0.2.0.dist-info/LICENSE.txt
ipicat-0.2.0.dist-info/METADATA
ipicat-0.2.0.dist-info/WHEEL
ipicat-0.2.0.dist-info/top_level.txt
ipicat-0.2.0.dist-info/RECORD
