Metadata-Version: 2.1
Name: ipicat
Version: 0.2.0
Summary: A Picat extension for IPython and Jupyter Notebook
Home-page: http://gitlab.com/minicz/ipicat
Maintainer: Marcio Minicz
Maintainer-email: marciominicz@gmail.com
License: MPL-2.0
Download-URL: http://gitlab.com/minicz/ipicat
Platform: Any
Classifier: Intended Audience :: Science/Research
Classifier: License :: OSI Approved :: Mozilla Public License 2.0 (MPL 2.0)
Classifier: Operating System :: OS Independent
Classifier: Programming Language :: Python
Classifier: Programming Language :: Python :: 3.5
Classifier: Programming Language :: Python :: 3.6
Classifier: Programming Language :: Python :: 3.7
Classifier: Topic :: Scientific/Engineering
Classifier: Topic :: Software Development
Classifier: Topic :: System :: Shells
Classifier: Framework :: IPython
Requires: jupyter
Requires-Dist: jupyter
